CHANGES.txt
LICENSE.txt
MANIFEST.in
README.txt
setup.py
js/__init__.py
js.jquery_textchildren.egg-info/PKG-INFO
js.jquery_textchildren.egg-info/SOURCES.txt
js.jquery_textchildren.egg-info/dependency_links.txt
js.jquery_textchildren.egg-info/entry_points.txt
js.jquery_textchildren.egg-info/namespace_packages.txt
js.jquery_textchildren.egg-info/not-zip-safe
js.jquery_textchildren.egg-info/requires.txt
js.jquery_textchildren.egg-info/top_level.txt
js/jquery_textchildren/__init__.py
js/jquery_textchildren/test_jquery_text_children.txt
js/jquery_textchildren/resources/jquery.textchildren.js