Metadata-Version: 1.0
Name: js.jquery-textchildren
Version: 0.1
Summary: Fanstatic packaging of jQuery Text Children
Home-page: UNKNOWN
Author: Fanstatic Developers
Author-email: fanstatic@googlegroups.com
License: BSD
Platform: UNKNOWN
